defs.v
/*Instruction decode*/
`define opcode 6:0
`define func3 14:12
`define func7 31:25

`define rd 11:7
`define rsa 19:15
`define rsb 24:20
`define IntSize 31:0

/*The defs related to rom*/
`define InstaddrBus 31:0
`define InstBus 31:0

/*Global defs*/
`define Rsten 1'b1
`define Rstdis 1'b0
`define ZWord 32'h00000000

`define CLOG2(x) (x<=2)?1:(x<=4)?2:(x<=8)?3:(x<=16)?4:(x<=32)?5:-1

/*opcode*/

execute.v
`include "defs.v"

module execute #(parameter XLEN=32)(
    input [3:0] ALUcrl,
    input [XLEN-1:0] ALU_src_a,
    input [XLEN-1:0] ALU_src_b,
    output reg [XLEN-1:0] ALUOut,
    output zero );
 
 assign zero = (ALUOut==`ZWord);

always @(ALUcrl,ALU_src_a,ALU_src_b)
begin
    case(ALUcrl)
        4'b0000: ALUOut <= ALU_src_a & ALU_src_b;
        4'b0001: ALUOut <= ALU_src_a | ALU_src_b;
        4'b0010: ALUOut <= ALU_src_a + ALU_src_b;
        4'b0110: ALUOut <= ALU_src_a - ALU_src_b;
        4'b0111: ALUOut <= (ALU_src_a < ALU_src_b)?1:0;
        4'b1100: ALUOut <= ~(ALU_src_a | ALU_src_b);
        default: ALUOut <= `ZWord;
    endcase
end

endmodule

regfile.v
`include "defs.v"
module regfile #(
    parameter NUM_REGS = 32,
    parameter XLEN = 32,
    parameter RSLEN = `CLOG2(NUM_REGS))(
    input clk,
    input rst,
    /*讀取rsa*/
    input [RSLEN-1:0] rsa_a,//rsa addr
    /*讀取rsb*/
    input [RSLEN-1:0] rsb_a,
    /*寫暫存器rd*/
    input [`IntSize] wb_data,
    input [RSLEN-1:0] w_baddr,
    input wb_e,
    /*輸出data1 2*/
    output [`IntSize] rsa_o,
    output [`IntSize] rsb_o     
);
reg [XLEN-1:0] rf[0:NUM_REGS-1];

wire we = wb_e &(|wb_addr);

assign rsa_o = (we&(rsa_a==wb_addr))?wb_data:rf[rsa_a];
assign rsb_o = (we&(rsb_a==wb_addr))?wb_data:rf[rsb_a];

always @(posedge clk)
begin
    if(rst==`Rsten)
    begin
        rf[0] <= `ZWord;
        rf[1] <= `ZWord;
        rf[2] <= `ZWord;
        rf[3] <= `ZWord;
        rf[4] <= `ZWord;
        rf[5] <= `ZWord;
        rf[6] <= `ZWord;
        rf[7] <= `ZWord;
        rf[8] <= `ZWord;
        rf[9] <= `ZWord;
        rf[10] <= `ZWord;
        rf[11] <= `ZWord;
        rf[12] <= `ZWord;
        rf[13] <= `ZWord;
        rf[14] <= `ZWord;
        rf[15] <= `ZWord;
        rf[16] <= `ZWord;
        rf[17] <= `ZWord;
        rf[18] <= `ZWord;
        rf[19] <= `ZWord;
        rf[20] <= `ZWord;
        rf[21] <= `ZWord;
        rf[22] <= `ZWord;
        rf[23] <= `ZWord;
        rf[24] <= `ZWord;
        rf[25] <= `ZWord;
        rf[26] <= `ZWord;
        rf[27] <= `ZWord;
        rf[28] <= `ZWord;
        rf[29] <= `ZWord;
        rf[30] <= `ZWord;
        rf[31] <= `ZWord; 
    end
   else 
   begin
       if(we)
       begin
            rf[wb_addr] <= wb_data;   
       end
   end 
   
end

endmodule

decode.v
`include "defs.v"
module decode #(parameter XLEN = 32)(
    input rst,
    input [`InstaddrBus] pc_i,
    input [`InstBus] inst_i,
    output reg regfile_we,
    output [4:0] rsa_a_o,
    output [4:0] rsb_a_o,
    output [4:0] rsd_o,
    output reg ALUSrc,
    output reg [3:0] ALUOp,
    output reg memtoreg);

/*decode*/
wire [XLEN-1:0] rv32_inst = inst_i;
wire [6:0] opcode = rv32_inst[`opcode];
wire [2:0] func3 = rv32_inst[`func3];
wire [6:0] func7 = rv32_inst[`func7];
wire [11:0] imm_I = rv32_inst[31:20];
wire [XLEN-1:0] imm;

wire rv32_based = (opcode[1:0]==2'b11)

/*R-type*/
wire rv32_op =(opcode[6:2] == 7'b01100);
wire rv32_func3_000 = (func3==3'b000);
wire rv32_func7_0100000 = (func7==7'b0100000);
wire rv32_func7_0000000 = (func7==7'b0000000);
wire rv32_sub = (rv32_func3_000 & rv32_func7_0100000);
wire rv32_add = (rv32_func3_000 & rv32_func7_0000000);

/*I-type*/
wire rv32_op_imm = (opcode[6:2]==7'b00100);
wire rv32_addi = (rv32_func3_000 & rv32_op_imm);

assign imm = imm_I;


/*Output data*/
assign rsa_a_o = rv32_inst[`rsa];
assign rsb_a_o = rv32_inst[`rsb];


always @ (*)
begin
    if(rst==`Rsten)
    begin
        regfile_we <= 1'b0;//write back enable
        ALUOp <= 1'b0;
        ALUSrc <= 1'b0;
    end
    else if(rv32_op == 1'b1)
    begin
        ALUSrc <= 1'b0;//1'b0 from regfile, 1'b1 from imm 
        regfile_we <= 1'b1;
        memtoreg <= 1'b0;//write back to regfile :1'b0 from ALU,1'b1 from memory
        if(rv32_sub == 1'b1) 
            begin
                ALUOp <= 4'b0110;//ALU_SUB
            end
        else if(rv32_add)
            begin
                ALUOp <= 4'b0010;//ALU_ADD
            end
    end
    else if() 
end

endmodule

if_id.v
`include "defs.v"
module if_id(
    input wire clk,
    input wire rst,
    input wire [`InstaddrBus] if_pc,
    input wire [`InstBus] if_inst,
    output reg [`InstaddrBus] id_pc,
    output reg [`InstBus] id_inst 
    );
    
    always @(posedge clk)
    begin
        if(rst == `Rsten)
        begin
            id_pc <=`ZWord;
            id_inst <=`ZWord;
        end
        else
        begin
            id_pc <= if_pc;
            id_inst <= if_inst;
        end
    end
endmodule

rom.v
`include "defs.v"
module rom ( input wire[5:0] addr, input wire ce, output reg[31:0] inst);

reg [31:0] rom [0:64];

initial	$readmemh ("rom.data",rom);

always  @(addr,ce)
begin	
	if ( ce == 1'b0 )begin
		inst <= `ZWord;
	end
	else if ( ce == 1'b1)begin
		inst <= rom[addr];
	end
end
endmodule

pc_reg.v
`include "defs.v"
module pc_reg ( input wire clk, input wire rst, output reg [`InstaddrBus] pc, output reg ce);

always @(posedge clk)
begin
       if(rst==1'b1)
       	begin
       		ce <= 1'b0;
	end
	else if(rst==1'b0) 
	begin
		ce <=1'b1;
	end

end

always @(posedge clk)
begin
	if(ce==1'b0)
	begin
		pc <= 32'h0;
	end
	else if(ce==1'b1)
	begin
		pc = pc + 1'b1;
	end

end
endmodule

core_top.v
`include "defs.v"
module core_top #(parameter XLEN=32,parameter NUM_REGS=32,parameter RSLEN = `CLOG2(NUM_REGS))(
	input wire clk, 
	input wire rst, 
	output wire [`InstBus] if_id_inst_o,
	output wire [`InstaddrBus] if_id_inst_pc);

	wire rom_ce0;
	wire [`InstBus] inst_o;
	wire [`InstaddrBus] inst_pc;
	wire [RSLEN-1:0] rsa_o;
	wire [RSLEN-1:0] rsb_o;
	wire [XLEN-1:0] rsa_data;
	wire [XLEN-1:0] rsb_data;
	wire regfile_we;
	wire [RSLEN-1:0] rsd_a;
	wire ALUSrc;
	wire [3:0] ALUOp;
	wire memtoreg;
	wire [XLEN-1:0] mem_data;
	wire [XLEN-1:0] wb_data;
	wire [XLEN-1:0] ALUOut;
	wire zero;
	/*instrution fetch*/
	pc_reg pc_reg0( .clk(clk), .rst(rst), .pc(inst_pc), .ce(rom_ce0));

	rom rom0( .addr(inst_pc), .ce(rom_ce0), .inst(inst_o));

	if_id if_id0( .clk(clk), .rst(rst), .if_pc(inst_pc), .if_inst(inst_o), .id_pc(if_id_inst_pc), .id_inst(if_id_inst_pc));
	/*Instruction decode*/
	decode decode0(.rst(rst), .pc_i(inst_pc), .inst_i(inst_o), .regfile_we(regfile_we), .rsa_a_o(rsa_o), .rsb_a_o(rsb_o), .rsd_o(rsd_a), .ALUSrc(ALUSrc), .ALUOp(ALUOp), .memtoreg(memtoreg));

	regfile regfile(.clk(clk), .rst(rst), .rsa_a(rsa_o), .rsb_a(rsb_o), .wb_data(wb_data), .wb_addr(rsd_a), .wb_e(regfile_we), .rsa_o(rsa_data), .rsb_o(rsb_data));
	/*execute*/
	execute execute0(.ALUcrl(ALUOp), .ALU_src_a(rsa_data), . ALU_src_b(rsb_data), .ALUOut(ALUOut), .zero(zero));
	/*memory read*/

	/*write back */
	assign wb_data = (memtoreg == 1'b1) ? mem_data:ALUOut;//data memory 待擴充

endmodule

cpu0_tb.v
module cpu0_tb;
reg CLOCK;
reg rst;
wire [31:0]  inst;
wire [31:0]  pc;

// block clock register and start the clock

initial
begin
	CLOCK = 1'b0;
	forever #10 CLOCK = ~CLOCK;
end

// setup rst and stop time

initial 
begin
	rst = 1'b1;

	#190 rst = 1'b0;

	#2000 $stop;
end

// test module

core_top core_top( .clk(CLOCK), .rst(rst), .if_id_inst_o(inst), .if_id_inst_pc(pc) );

initial begin
	$dumpfile("cpu0_tb.vcd");
	$dumpvars(0,cpu0_tb);
end

endmodule

cpu0_tb.vcd
$date
	Wed Dec 23 13:48:54 2020
$end
$version
	Icarus Verilog
$end
$timescale
	1s
$end
$scope module cpu0_tb $end
$var wire 32 ! inst [31:0] $end
$var wire 32 " pc [31:0] $end
$var reg 1 # CLOCK $end
$var reg 1 $ rst $end
$scope module core_top $end
$var wire 1 # clk $end
$var wire 32 % if_id_inst_o [31:0] $end
$var wire 32 & if_id_inst_pc [31:0] $end
$var wire 32 ' mem_data [31:0] $end
$var wire 5 ( rsd_a [4:0] $end
$var wire 1 $ rst $end
$var wire 1 ) zero $end
$var wire 32 * wb_data [31:0] $end
$var wire 5 + rsb_o [4:0] $end
$var wire 32 , rsb_data [31:0] $end
$var wire 5 - rsa_o [4:0] $end
$var wire 32 . rsa_data [31:0] $end
$var wire 1 / rom_ce0 $end
$var wire 1 0 regfile_we $end
$var wire 1 1 memtoreg $end
$var wire 32 2 inst_pc [31:0] $end
$var wire 32 3 inst_o [31:0] $end
$var wire 1 4 ALUSrc $end
$var wire 32 5 ALUOut [31:0] $end
$var wire 4 6 ALUOp [3:0] $end
$scope module decode0 $end
$var wire 5 7 rsd_o [4:0] $end
$var wire 1 $ rst $end
$var wire 1 8 rv32_add $end
$var wire 1 9 rv32_addi $end
$var wire 32 : rv32_inst [31:0] $end
$var wire 1 ; rv32_sub $end
$var wire 1 < rv32_op_imm $end
$var wire 1 = rv32_op $end
$var wire 1 > rv32_func7_0100000 $end
$var wire 1 ? rv32_func7_0000000 $end
$var wire 1 @ rv32_func3_000 $end
$var wire 5 A rsb_a_o [4:0] $end
$var wire 5 B rsa_a_o [4:0] $end
$var wire 32 C pc_i [31:0] $end
$var wire 7 D opcode [6:0] $end
$var wire 32 E inst_i [31:0] $end
$var wire 12 F imm_I [11:0] $end
$var wire 32 G imm [31:0] $end
$var wire 7 H func7 [6:0] $end
$var wire 3 I func3 [2:0] $end
$var reg 4 J ALUOp [3:0] $end
$var reg 1 4 ALUSrc $end
$var reg 1 1 memtoreg $end
$var reg 1 0 regfile_we $end
$upscope $end
$scope module execute0 $end
$var wire 4 K ALUcrl [3:0] $end
$var wire 1 ) zero $end
$var wire 32 L ALU_src_b [31:0] $end
$var wire 32 M ALU_src_a [31:0] $end
$var reg 32 N ALUOut [31:0] $end
$upscope $end
$scope module if_id0 $end
$var wire 1 # clk $end
$var wire 1 $ rst $end
$var wire 32 O if_pc [31:0] $end
$var wire 32 P if_inst [31:0] $end
$var reg 32 Q id_inst [31:0] $end
$var reg 32 R id_pc [31:0] $end
$upscope $end
$scope module pc_reg0 $end
$var wire 1 # clk $end
$var wire 1 $ rst $end
$var reg 1 / ce $end
$var reg 32 S pc [31:0] $end
$upscope $end
$scope module regfile $end
$var wire 1 # clk $end
$var wire 5 T rsa_a [4:0] $end
$var wire 5 U rsb_a [4:0] $end
$var wire 1 $ rst $end
$var wire 5 V wb_addr [4:0] $end
$var wire 32 W wb_data [31:0] $end
$var wire 1 0 wb_e $end
$var wire 1 X we $end
$var wire 32 Y rsb_o [31:0] $end
$var wire 32 Z rsa_o [31:0] $end
$upscope $end
$scope module rom0 $end
$var wire 6 [ addr [5:0] $end
$var wire 1 / ce $end
$var reg 32 \ inst [31:0] $end
$upscope $end
$upscope $end
$upscope $end
$enddefinitions $end
#0
$dumpvars
bx \
bx [
bx Z
bx Y
0X
bx W
bz V
bx U
bx T
bx S
bx R
bx Q
bx P
bx O
bx N
bx M
bx L
b0 K
b0 J
bx I
bx H
b0xxxxxxxxxxxx G
bx F
bx E
bx D
bx C
bx B
bx A
x@
x?
x>
x=
x<
x;
bx :
x9
x8
bz 7
b0 6
bx 5
04
bx 3
bx 2
x1
00
x/
bx .
bx -
bx ,
bx +
bx *
x)
bz (
bz '
bx &
bz %
1$
0#
bx "
bz !
$end
#10
1)
b0 5
b0 N
09
0;
18
b0 .
b0 M
b0 Z
b0 ,
b0 L
b0 Y
0=
0<
b0 D
1@
b0 I
0>
1?
b0 H
b0 G
b0 F
b0 -
b0 B
b0 T
b0 +
b0 A
b0 U
b0 :
b0 3
b0 E
b0 P
b0 \
0/
b0 "
b0 &
b0 Q
b0 R
1#
#20
0#
#30
b0 [
b0 2
b0 C
b0 O
b0 S
1#
#40
0#
#50
1#
#60
0#
#70
1#
#80
0#
#90
1#
#100
0#
#110
1#
#120
0#
#130
1#
#140
0#
#150
1#
#160
0#
#170
1#
#180
0#
#190
b0 *
b0 W
xX
b10 6
b10 J
b10 K
01
10
1=
b110011 D
b1 G
b1 F
b10 -
b10 B
b10 T
b1 +
b1 A
b1 U
b100010000000110110011 :
b100010000000110110011 3
b100010000000110110011 E
b100010000000110110011 P
b100010000000110110011 \
1/
1#
0$
#200
0#
#210
b110 6
b110 J
b110 K
1;
08
1>
0?
b100000 H
b10000000001 G
b10000000001 F
b1000000000100010000000110110011 :
b1000000000100010000000110110011 3
b1000000000100010000000110110011 E
b1000000000100010000000110110011 P
b1000000000100010000000110110011 \
b0x000x0000000xx0xx00xx "
b0x000x0000000xx0xx00xx &
b100010000000110110011 Q
b1 [
b1 2
b1 C
b1 O
b1 S
1#
#220
0#
#230
b10 6
b10 J
b10 K
0;
18
0>
1?
b0 H
b11 G
b11 F
b100 -
b100 B
b100 T
b11 +
b11 A
b11 U
b1100100000001010110011 :
b1100100000001010110011 3
b1100100000001010110011 E
b1100100000001010110011 P
b1100100000001010110011 \
b1000000000100010000000110110011 Q
b0x000000000x000x0000000xx0xx001x "
b0x000000000x000x0000000xx0xx001x &
b10 R
b10 [
b10 2
b10 C
b10 O
b10 S
1#
#240
0#
#250
b110 6
b110 J
b110 K
1;
08
1>
0?
b100000 H
b10000000011 G
b10000000011 F
b1000000001100100000001010110011 :
b1000000001100100000001010110011 3
b1000000001100100000001010110011 E
b1000000001100100000001010110011 P
b1000000001100100000001010110011 \
b0xx00x0000000x0x0xx001x "
b0xx00x0000000x0x0xx001x &
b1100100000001010110011 Q
b11 [
b11 2
b11 C
b11 O
b11 S
1#
#260
0#
#270
bx *
bx W
x)
bx 5
bx N
x9
x;
x8
bx .
bx M
bx Z
bx ,
bx L
bx Y
x=
x<
bx D
x@
bx I
x>
x?
bx H
b0xxxxxxxxxxxx G
bx F
bx -
bx B
bx T
bx +
bx A
bx U
bx :
bx 3
bx E
bx P
bx \
b1000000001100100000001010110011 Q
b0x00000000xx00x0000000x0x0xx0xxx "
b0x00000000xx00x0000000x0x0xx0xxx &
b100 R
b100 [
b100 2
b100 C
b100 O
b100 S
1#
#280
0#
#290
bx "
bx &
bx Q
b101 [
b101 2
b101 C
b101 O
b101 S
1#
#300
0#
#310
b110 R
b110 [
b110 2
b110 C
b110 O
b110 S
1#
#320
0#
#330
b111 [
b111 2
b111 C
b111 O
b111 S
1#
#340
0#
#350
b1000 R
b1000 [
b1000 2
b1000 C
b1000 O
b1000 S
1#
#360
0#
#370
b1001 [
b1001 2
b1001 C
b1001 O
b1001 S
1#
#380
0#
#390
b1010 R
b1010 [
b1010 2
b1010 C
b1010 O
b1010 S
1#
#400
0#
#410
b1011 [
b1011 2
b1011 C
b1011 O
b1011 S
1#
#420
0#
#430
b1100 R
b1100 [
b1100 2
b1100 C
b1100 O
b1100 S
1#
#440
0#
#450
b1101 [
b1101 2
b1101 C
b1101 O
b1101 S
1#
#460
0#
#470
b1110 R
b1110 [
b1110 2
b1110 C
b1110 O
b1110 S
1#
#480
0#
#490
b1111 [
b1111 2
b1111 C
b1111 O
b1111 S
1#
#500
0#
#510
b10000 R
b10000 [
b10000 2
b10000 C
b10000 O
b10000 S
1#
#520
0#
#530
b10001 [
b10001 2
b10001 C
b10001 O
b10001 S
1#
#540
0#
#550
b10010 R
b10010 [
b10010 2
b10010 C
b10010 O
b10010 S
1#
#560
0#
#570
b10011 [
b10011 2
b10011 C
b10011 O
b10011 S
1#
#580
0#
#590
b10100 R
b10100 [
b10100 2
b10100 C
b10100 O
b10100 S
1#
#600
0#
#610
b10101 [
b10101 2
b10101 C
b10101 O
b10101 S
1#
#620
0#
#630
b10110 R
b10110 [
b10110 2
b10110 C
b10110 O
b10110 S
1#
#640
0#
#650
b10111 [
b10111 2
b10111 C
b10111 O
b10111 S
1#
#660
0#
#670
b11000 R
b11000 [
b11000 2
b11000 C
b11000 O
b11000 S
1#
#680
0#
#690
b11001 [
b11001 2
b11001 C
b11001 O
b11001 S
1#
#700
0#
#710
b11010 R
b11010 [
b11010 2
b11010 C
b11010 O
b11010 S
1#
#720
0#
#730
b11011 [
b11011 2
b11011 C
b11011 O
b11011 S
1#
#740
0#
#750
b11100 R
b11100 [
b11100 2
b11100 C
b11100 O
b11100 S
1#
#760
0#
#770
b11101 [
b11101 2
b11101 C
b11101 O
b11101 S
1#
#780
0#
#790
b11110 R
b11110 [
b11110 2
b11110 C
b11110 O
b11110 S
1#
#800
0#
#810
b11111 [
b11111 2
b11111 C
b11111 O
b11111 S
1#
#820
0#
#830
b100000 R
b100000 [
b100000 2
b100000 C
b100000 O
b100000 S
1#
#840
0#
#850
b100001 [
b100001 2
b100001 C
b100001 O
b100001 S
1#
#860
0#
#870
b100010 R
b100010 [
b100010 2
b100010 C
b100010 O
b100010 S
1#
#880
0#
#890
b100011 [
b100011 2
b100011 C
b100011 O
b100011 S
1#
#900
0#
#910
b100100 R
b100100 [
b100100 2
b100100 C
b100100 O
b100100 S
1#
#920
0#
#930
b100101 [
b100101 2
b100101 C
b100101 O
b100101 S
1#
#940
0#
#950
b100110 R
b100110 [
b100110 2
b100110 C
b100110 O
b100110 S
1#
#960
0#
#970
b100111 [
b100111 2
b100111 C
b100111 O
b100111 S
1#
#980
0#
#990
b101000 R
b101000 [
b101000 2
b101000 C
b101000 O
b101000 S
1#
#1000
0#
#1010
b101001 [
b101001 2
b101001 C
b101001 O
b101001 S
1#
#1020
0#
#1030
b101010 R
b101010 [
b101010 2
b101010 C
b101010 O
b101010 S
1#
#1040
0#
#1050
b101011 [
b101011 2
b101011 C
b101011 O
b101011 S
1#
#1060
0#
#1070
b101100 R
b101100 [
b101100 2
b101100 C
b101100 O
b101100 S
1#
#1080
0#
#1090
b101101 [
b101101 2
b101101 C
b101101 O
b101101 S
1#
#1100
0#
#1110
b101110 R
b101110 [
b101110 2
b101110 C
b101110 O
b101110 S
1#
#1120
0#
#1130
b101111 [
b101111 2
b101111 C
b101111 O
b101111 S
1#
#1140
0#
#1150
b110000 R
b110000 [
b110000 2
b110000 C
b110000 O
b110000 S
1#
#1160
0#
#1170
b110001 [
b110001 2
b110001 C
b110001 O
b110001 S
1#
#1180
0#
#1190
b110010 R
b110010 [
b110010 2
b110010 C
b110010 O
b110010 S
1#
#1200
0#
#1210
b110011 [
b110011 2
b110011 C
b110011 O
b110011 S
1#
#1220
0#
#1230
b110100 R
b110100 [
b110100 2
b110100 C
b110100 O
b110100 S
1#
#1240
0#
#1250
b110101 [
b110101 2
b110101 C
b110101 O
b110101 S
1#
#1260
0#
#1270
b110110 R
b110110 [
b110110 2
b110110 C
b110110 O
b110110 S
1#
#1280
0#
#1290
b110111 [
b110111 2
b110111 C
b110111 O
b110111 S
1#
#1300
0#
#1310
b111000 R
b111000 [
b111000 2
b111000 C
b111000 O
b111000 S
1#
#1320
0#
#1330
b111001 [
b111001 2
b111001 C
b111001 O
b111001 S
1#
#1340
0#
#1350
b111010 R
b111010 [
b111010 2
b111010 C
b111010 O
b111010 S
1#
#1360
0#
#1370
b111011 [
b111011 2
b111011 C
b111011 O
b111011 S
1#
#1380
0#
#1390
b111100 R
b111100 [
b111100 2
b111100 C
b111100 O
b111100 S
1#
#1400
0#
#1410
b111101 [
b111101 2
b111101 C
b111101 O
b111101 S
1#
#1420
0#
#1430
b111110 R
b111110 [
b111110 2
b111110 C
b111110 O
b111110 S
1#
#1440
0#
#1450
b111111 [
b111111 2
b111111 C
b111111 O
b111111 S
1#
#1460
0#
#1470
b10 6
b10 J
b10 K
09
0;
18
1=
0<
b110011 D
1@
b0 I
0>
1?
b0 H
b1 G
b1 F
b10 -
b10 B
b10 T
b1 +
b1 A
b1 U
b100010000000110110011 :
b100010000000110110011 3
b100010000000110110011 E
b100010000000110110011 P
b100010000000110110011 \
b1000000 R
b0 [
b1000000 2
b1000000 C
b1000000 O
b1000000 S
1#
#1480
0#
#1490
b110 6
b110 J
b110 K
1;
08
1>
0?
b100000 H
b10000000001 G
b10000000001 F
b1000000000100010000000110110011 :
b1000000000100010000000110110011 3
b1000000000100010000000110110011 E
b1000000000100010000000110110011 P
b1000000000100010000000110110011 \
b0x000x0000000xxxxx00xx "
b0x000x0000000xxxxx00xx &
b100010000000110110011 Q
b1 [
b1000001 2
b1000001 C
b1000001 O
b1000001 S
1#
#1500
0#
#1510
b10 6
b10 J
b10 K
0;
18
0>
1?
b0 H
b11 G
b11 F
b100 -
b100 B
b100 T
b11 +
b11 A
b11 U
b1100100000001010110011 :
b1100100000001010110011 3
b1100100000001010110011 E
b1100100000001010110011 P
b1100100000001010110011 \
b1000000000100010000000110110011 Q
b0x000000000x000x0000000xxxxx001x "
b0x000000000x000x0000000xxxxx001x &
b1000010 R
b10 [
b1000010 2
b1000010 C
b1000010 O
b1000010 S
1#
#1520
0#
#1530
b110 6
b110 J
b110 K
1;
08
1>
0?
b100000 H
b10000000011 G
b10000000011 F
b1000000001100100000001010110011 :
b1000000001100100000001010110011 3
b1000000001100100000001010110011 E
b1000000001100100000001010110011 P
b1000000001100100000001010110011 \
b0xx00x0000000x0xxxx001x "
b0xx00x0000000x0xxxx001x &
b1100100000001010110011 Q
b11 [
b1000011 2
b1000011 C
b1000011 O
b1000011 S
1#
#1540
0#
#1550
x9
x;
x8
x=
x<
bx D
x@
bx I
x>
x?
bx H
b0xxxxxxxxxxxx G
bx F
bx -
bx B
bx T
bx +
bx A
bx U
bx :
bx 3
bx E
bx P
bx \
b1000000001100100000001010110011 Q
b0x00000000xx00x0000000x0xxxx0xxx "
b0x00000000xx00x0000000x0xxxx0xxx &
b1000100 R
b100 [
b1000100 2
b1000100 C
b1000100 O
b1000100 S
1#
#1560
0#
#1570
bx "
bx &
bx Q
b101 [
b1000101 2
b1000101 C
b1000101 O
b1000101 S
1#
#1580
0#
#1590
b1000110 R
b110 [
b1000110 2
b1000110 C
b1000110 O
b1000110 S
1#
#1600
0#
#1610
b111 [
b1000111 2
b1000111 C
b1000111 O
b1000111 S
1#
#1620
0#
#1630
b1001000 R
b1000 [
b1001000 2
b1001000 C
b1001000 O
b1001000 S
1#
#1640
0#
#1650
b1001 [
b1001001 2
b1001001 C
b1001001 O
b1001001 S
1#
#1660
0#
#1670
b1001010 R
b1010 [
b1001010 2
b1001010 C
b1001010 O
b1001010 S
1#
#1680
0#
#1690
b1011 [
b1001011 2
b1001011 C
b1001011 O
b1001011 S
1#
#1700
0#
#1710
b1001100 R
b1100 [
b1001100 2
b1001100 C
b1001100 O
b1001100 S
1#
#1720
0#
#1730
b1101 [
b1001101 2
b1001101 C
b1001101 O
b1001101 S
1#
#1740
0#
#1750
b1001110 R
b1110 [
b1001110 2
b1001110 C
b1001110 O
b1001110 S
1#
#1760
0#
#1770
b1111 [
b1001111 2
b1001111 C
b1001111 O
b1001111 S
1#
#1780
0#
#1790
b1010000 R
b10000 [
b1010000 2
b1010000 C
b1010000 O
b1010000 S
1#
#1800
0#
#1810
b10001 [
b1010001 2
b1010001 C
b1010001 O
b1010001 S
1#
#1820
0#
#1830
b1010010 R
b10010 [
b1010010 2
b1010010 C
b1010010 O
b1010010 S
1#
#1840
0#
#1850
b10011 [
b1010011 2
b1010011 C
b1010011 O
b1010011 S
1#
#1860
0#
#1870
b1010100 R
b10100 [
b1010100 2
b1010100 C
b1010100 O
b1010100 S
1#
#1880
0#
#1890
b10101 [
b1010101 2
b1010101 C
b1010101 O
b1010101 S
1#
#1900
0#
#1910
b1010110 R
b10110 [
b1010110 2
b1010110 C
b1010110 O
b1010110 S
1#
#1920
0#
#1930
b10111 [
b1010111 2
b1010111 C
b1010111 O
b1010111 S
1#
#1940
0#
#1950
b1011000 R
b11000 [
b1011000 2
b1011000 C
b1011000 O
b1011000 S
1#
#1960
0#
#1970
b11001 [
b1011001 2
b1011001 C
b1011001 O
b1011001 S
1#
#1980
0#
#1990
b1011010 R
b11010 [
b1011010 2
b1011010 C
b1011010 O
b1011010 S
1#
#2000
0#
#2010
b11011 [
b1011011 2
b1011011 C
b1011011 O
b1011011 S
1#
#2020
0#
#2030
b1011100 R
b11100 [
b1011100 2
b1011100 C
b1011100 O
b1011100 S
1#
#2040
0#
#2050
b11101 [
b1011101 2
b1011101 C
b1011101 O
b1011101 S
1#
#2060
0#
#2070
b1011110 R
b11110 [
b1011110 2
b1011110 C
b1011110 O
b1011110 S
1#
#2080
0#
#2090
b11111 [
b1011111 2
b1011111 C
b1011111 O
b1011111 S
1#
#2100
0#
#2110
b1100000 R
b100000 [
b1100000 2
b1100000 C
b1100000 O
b1100000 S
1#
#2120
0#
#2130
b100001 [
b1100001 2
b1100001 C
b1100001 O
b1100001 S
1#
#2140
0#
#2150
b1100010 R
b100010 [
b1100010 2
b1100010 C
b1100010 O
b1100010 S
1#
#2160
0#
#2170
b100011 [
b1100011 2
b1100011 C
b1100011 O
b1100011 S
1#
