rom.v
module rom ( input wire[5:0] addr, input wire ce, output reg[31:0] inst);

reg [31:0] rom [0:63];

initial	$readmemh ("rom.data",rom);

always  @(addr,ce)
begin	
	if ( ce == 1'b0 )begin
		inst <= 32'h0;
	end
	else if ( ce == 1'b1)begin
		inst <= rom[addr];
	end
end
endmodule

pc_reg.v
module pc_reg ( input wire clk, input wire rst, output reg [5:0] pc, output reg ce);

always @(posedge clk)
begin
       if(rst==1'b1)
       	begin
       		ce <= 1'b0;
	end
	else if(rst==1'b0) 
	begin
		ce <=1'b1;
	end

end

always @(posedge clk)
begin
	if(ce==1'b0)
	begin
		pc <= 6'h00;
	end
	else if(ce==1'b1)
	begin
		pc = pc + 1'b1;
	end

end
endmodule

inst_fetch.v
module inst_fetch (input wire clk, input wire rst, output wire [31:0] inst_o);

	wire [5:0] pc0;
	wire rom_ce0;
	
	pc_reg pc_reg0( .clk(clk), .rst(rst), .pc(pc0), .ce(rom_ce0));

	rom rom0( .addr(pc0), .ce(rom_ce0), .inst(inst_o));

endmodule

cpu0_tb.v
module cpu0_tb;
reg CLOCK;
reg rst;
wire [31:0]  inst;

// block clock register and start the clock

initial
begin
	CLOCK = 1'b0;
	forever #10 CLOCK = ~CLOCK;
end

// setup rst and stop time

initial 
begin
	rst = 1'b1;

	#190 rst = 1'b0;

	#2000 $stop;
end

// test module

inst_fetch inst_fetch0( .clk(CLOCK), .rst(rst), .inst_o(inst) );

initial begin
	$dumpfile("cpu0_tb.vcd");
	$dumpvars(0,cpu0_tb);
end

endmodule

cpu0_tb.vcd
$date
	Tue Oct  6 00:19:06 2020
$end
$version
	Icarus Verilog
$end
$timescale
	1s
$end
$scope module cpu0_tb $end
$var wire 32 ! inst [31:0] $end
$var reg 1 " CLOCK $end
$var reg 1 # rst $end
$scope module inst_fetch0 $end
$var wire 1 " clk $end
$var wire 1 # rst $end
$var wire 1 $ rom_ce0 $end
$var wire 6 % pc0 [5:0] $end
$var wire 32 & inst_o [31:0] $end
$scope module pc_reg0 $end
$var wire 1 " clk $end
$var wire 1 # rst $end
$var reg 1 $ ce $end
$var reg 6 ' pc [5:0] $end
$upscope $end
$scope module rom0 $end
$var wire 6 ( addr [5:0] $end
$var wire 1 $ ce $end
$var reg 32 ) inst [31:0] $end
$upscope $end
$upscope $end
$upscope $end
$enddefinitions $end
#0
$dumpvars
bx )
bx (
bx '
bx &
bx %
x$
1#
0"
bx !
$end
#10
b0 !
b0 &
b0 )
0$
1"
#20
0"
#30
b0 %
b0 '
b0 (
1"
#40
0"
#50
1"
#60
0"
#70
1"
#80
0"
#90
1"
#100
0"
#110
1"
#120
0"
#130
1"
#140
0"
#150
1"
#160
0"
#170
1"
#180
0"
#190
b11000000101000000000110100000000 !
b11000000101000000000110100000000 &
b11000000101000000000110100000000 )
1$
1"
0#
#200
0"
#210
b100010000000000010001 !
b100010000000000010001 &
b100010000000000010001 )
b1 %
b1 '
b1 (
1"
#220
0"
#230
b10001000000000001000100000000 !
b10001000000000001000100000000 &
b10001000000000001000100000000 )
b10 %
b10 '
b10 (
1"
#240
0"
#250
b10000000100000001000000010000 !
b10000000100000001000000010000 &
b10000000100000001000000010000 )
b11 %
b11 '
b11 (
1"
#260
0"
#270
b1000000010000000100000001 !
b1000000010000000100000001 &
b1000000010000000100000001 )
b100 %
b100 '
b100 (
1"
#280
0"
#290
b1000100000001000100000001 !
b1000100000001000100000001 &
b1000100000001000100000001 )
b101 %
b101 '
b101 (
1"
#300
0"
#310
b100000000000100000000 !
b100000000000100000000 &
b100000000000100000000 )
b110 %
b110 '
b110 (
1"
#320
0"
#330
b1000100010000000000000001 !
b1000100010000000000000001 &
b1000100010000000000000001 )
b111 %
b111 '
b111 (
1"
#340
0"
#350
b0 !
b0 &
b0 )
b1000 %
b1000 '
b1000 (
1"
#360
0"
#370
b100010000000000010001 !
b100010000000000010001 &
b100010000000000010001 )
b1001 %
b1001 '
b1001 (
1"
#380
0"
#390
b10001000000000001000100000000 !
b10001000000000001000100000000 &
b10001000000000001000100000000 )
b1010 %
b1010 '
b1010 (
1"
#400
0"
#410
b10000000100000001000000010000 !
b10000000100000001000000010000 &
b10000000100000001000000010000 )
b1011 %
b1011 '
b1011 (
1"
#420
0"
#430
b1000000010000000100000001 !
b1000000010000000100000001 &
b1000000010000000100000001 )
b1100 %
b1100 '
b1100 (
1"
#440
0"
#450
b1000100000001000100000001 !
b1000100000001000100000001 &
b1000100000001000100000001 )
b1101 %
b1101 '
b1101 (
1"
#460
0"
#470
b100000000000100000000 !
b100000000000100000000 &
b100000000000100000000 )
b1110 %
b1110 '
b1110 (
1"
#480
0"
#490
b1000100010000000000000001 !
b1000100010000000000000001 &
b1000100010000000000000001 )
b1111 %
b1111 '
b1111 (
1"
#500
0"
#510
b0 !
b0 &
b0 )
b10000 %
b10000 '
b10000 (
1"
#520
0"
#530
b100010000000000010001 !
b100010000000000010001 &
b100010000000000010001 )
b10001 %
b10001 '
b10001 (
1"
#540
0"
#550
b10001000000000001000100000000 !
b10001000000000001000100000000 &
b10001000000000001000100000000 )
b10010 %
b10010 '
b10010 (
1"
#560
0"
#570
b10000000100000001000000010000 !
b10000000100000001000000010000 &
b10000000100000001000000010000 )
b10011 %
b10011 '
b10011 (
1"
#580
0"
#590
b1000000010000000100000001 !
b1000000010000000100000001 &
b1000000010000000100000001 )
b10100 %
b10100 '
b10100 (
1"
#600
0"
#610
b1000100000001000100000001 !
b1000100000001000100000001 &
b1000100000001000100000001 )
b10101 %
b10101 '
b10101 (
1"
#620
0"
#630
b100000000000100000000 !
b100000000000100000000 &
b100000000000100000000 )
b10110 %
b10110 '
b10110 (
1"
#640
0"
#650
b1000100010000000000000001 !
b1000100010000000000000001 &
b1000100010000000000000001 )
b10111 %
b10111 '
b10111 (
1"
#660
0"
#670
b0 !
b0 &
b0 )
b11000 %
b11000 '
b11000 (
1"
#680
0"
#690
b100010000000000010001 !
b100010000000000010001 &
b100010000000000010001 )
b11001 %
b11001 '
b11001 (
1"
#700
0"
#710
b10001000000000001000100000000 !
b10001000000000001000100000000 &
b10001000000000001000100000000 )
b11010 %
b11010 '
b11010 (
1"
#720
0"
#730
b10000000100000001000000010000 !
b10000000100000001000000010000 &
b10000000100000001000000010000 )
b11011 %
b11011 '
b11011 (
1"
#740
0"
#750
b1000000010000000100000001 !
b1000000010000000100000001 &
b1000000010000000100000001 )
b11100 %
b11100 '
b11100 (
1"
#760
0"
#770
b1000100000001000100000001 !
b1000100000001000100000001 &
b1000100000001000100000001 )
b11101 %
b11101 '
b11101 (
1"
#780
0"
#790
b100000000000100000000 !
b100000000000100000000 &
b100000000000100000000 )
b11110 %
b11110 '
b11110 (
1"
#800
0"
#810
b1000100010000000000000001 !
b1000100010000000000000001 &
b1000100010000000000000001 )
b11111 %
b11111 '
b11111 (
1"
#820
0"
#830
b0 !
b0 &
b0 )
b100000 %
b100000 '
b100000 (
1"
#840
0"
#850
b100010000000000010001 !
b100010000000000010001 &
b100010000000000010001 )
b100001 %
b100001 '
b100001 (
1"
#860
0"
#870
b10001000000000001000100000000 !
b10001000000000001000100000000 &
b10001000000000001000100000000 )
b100010 %
b100010 '
b100010 (
1"
#880
0"
#890
b10000000100000001000000010000 !
b10000000100000001000000010000 &
b10000000100000001000000010000 )
b100011 %
b100011 '
b100011 (
1"
#900
0"
#910
b1000000010000000100000001 !
b1000000010000000100000001 &
b1000000010000000100000001 )
b100100 %
b100100 '
b100100 (
1"
#920
0"
#930
b1000100000001000100000001 !
b1000100000001000100000001 &
b1000100000001000100000001 )
b100101 %
b100101 '
b100101 (
1"
#940
0"
#950
b100000000000100000000 !
b100000000000100000000 &
b100000000000100000000 )
b100110 %
b100110 '
b100110 (
1"
#960
0"
#970
b1000100010000000000000001 !
b1000100010000000000000001 &
b1000100010000000000000001 )
b100111 %
b100111 '
b100111 (
1"
#980
0"
#990
b0 !
b0 &
b0 )
b101000 %
b101000 '
b101000 (
1"
#1000
0"
#1010
b100010000000000010001 !
b100010000000000010001 &
b100010000000000010001 )
b101001 %
b101001 '
b101001 (
1"
#1020
0"
#1030
b10001000000000001000100000000 !
b10001000000000001000100000000 &
b10001000000000001000100000000 )
b101010 %
b101010 '
b101010 (
1"
#1040
0"
#1050
b10000000100000001000000010000 !
b10000000100000001000000010000 &
b10000000100000001000000010000 )
b101011 %
b101011 '
b101011 (
1"
#1060
0"
#1070
b1000000010000000100000001 !
b1000000010000000100000001 &
b1000000010000000100000001 )
b101100 %
b101100 '
b101100 (
1"
#1080
0"
#1090
b1000100000001000100000001 !
b1000100000001000100000001 &
b1000100000001000100000001 )
b101101 %
b101101 '
b101101 (
1"
#1100
0"
#1110
b100000000000100000000 !
b100000000000100000000 &
b100000000000100000000 )
b101110 %
b101110 '
b101110 (
1"
#1120
0"
#1130
b1000100010000000000000001 !
b1000100010000000000000001 &
b1000100010000000000000001 )
b101111 %
b101111 '
b101111 (
1"
#1140
0"
#1150
b0 !
b0 &
b0 )
b110000 %
b110000 '
b110000 (
1"
#1160
0"
#1170
b100010000000000010001 !
b100010000000000010001 &
b100010000000000010001 )
b110001 %
b110001 '
b110001 (
1"
#1180
0"
#1190
b10001000000000001000100000000 !
b10001000000000001000100000000 &
b10001000000000001000100000000 )
b110010 %
b110010 '
b110010 (
1"
#1200
0"
#1210
b10000000100000001000000010000 !
b10000000100000001000000010000 &
b10000000100000001000000010000 )
b110011 %
b110011 '
b110011 (
1"
#1220
0"
#1230
b1000000010000000100000001 !
b1000000010000000100000001 &
b1000000010000000100000001 )
b110100 %
b110100 '
b110100 (
1"
#1240
0"
#1250
b1000100000001000100000001 !
b1000100000001000100000001 &
b1000100000001000100000001 )
b110101 %
b110101 '
b110101 (
1"
#1260
0"
#1270
b100000000000100000000 !
b100000000000100000000 &
b100000000000100000000 )
b110110 %
b110110 '
b110110 (
1"
#1280
0"
#1290
b1000100010000000000000001 !
b1000100010000000000000001 &
b1000100010000000000000001 )
b110111 %
b110111 '
b110111 (
1"
#1300
0"
#1310
b0 !
b0 &
b0 )
b111000 %
b111000 '
b111000 (
1"
#1320
0"
#1330
b100010000000000010001 !
b100010000000000010001 &
b100010000000000010001 )
b111001 %
b111001 '
b111001 (
1"
#1340
0"
#1350
b10001000000000001000100000000 !
b10001000000000001000100000000 &
b10001000000000001000100000000 )
b111010 %
b111010 '
b111010 (
1"
#1360
0"
#1370
b10000000100000001000000010000 !
b10000000100000001000000010000 &
b10000000100000001000000010000 )
b111011 %
b111011 '
b111011 (
1"
#1380
0"
#1390
b1000000010000000100000001 !
b1000000010000000100000001 &
b1000000010000000100000001 )
b111100 %
b111100 '
b111100 (
1"
#1400
0"
#1410
b1000100000001000100000001 !
b1000100000001000100000001 &
b1000100000001000100000001 )
b111101 %
b111101 '
b111101 (
1"
#1420
0"
#1430
b100000000000100000000 !
b100000000000100000000 &
b100000000000100000000 )
b111110 %
b111110 '
b111110 (
1"
#1440
0"
#1450
b1000100010000000000000001 !
b1000100010000000000000001 &
b1000100010000000000000001 )
b111111 %
b111111 '
b111111 (
1"
#1460
0"
#1470
b11000000101000000000110100000000 !
b11000000101000000000110100000000 &
b11000000101000000000110100000000 )
b0 %
b0 '
b0 (
1"
#1480
0"
#1490
b100010000000000010001 !
b100010000000000010001 &
b100010000000000010001 )
b1 %
b1 '
b1 (
1"
#1500
0"
#1510
b10001000000000001000100000000 !
b10001000000000001000100000000 &
b10001000000000001000100000000 )
b10 %
b10 '
b10 (
1"
#1520
0"
#1530
b10000000100000001000000010000 !
b10000000100000001000000010000 &
b10000000100000001000000010000 )
b11 %
b11 '
b11 (
1"
#1540
0"
#1550
b1000000010000000100000001 !
b1000000010000000100000001 &
b1000000010000000100000001 )
b100 %
b100 '
b100 (
1"
#1560
0"
#1570
b1000100000001000100000001 !
b1000100000001000100000001 &
b1000100000001000100000001 )
b101 %
b101 '
b101 (
1"
#1580
0"
#1590
b100000000000100000000 !
b100000000000100000000 &
b100000000000100000000 )
b110 %
b110 '
b110 (
1"
#1600
0"
#1610
b1000100010000000000000001 !
b1000100010000000000000001 &
b1000100010000000000000001 )
b111 %
b111 '
b111 (
1"
#1620
0"
#1630
b0 !
b0 &
b0 )
b1000 %
b1000 '
b1000 (
1"
#1640
0"
#1650
b100010000000000010001 !
b100010000000000010001 &
b100010000000000010001 )
b1001 %
b1001 '
b1001 (
1"
#1660
0"
#1670
b10001000000000001000100000000 !
b10001000000000001000100000000 &
b10001000000000001000100000000 )
b1010 %
b1010 '
b1010 (
1"
#1680
0"
#1690
b10000000100000001000000010000 !
b10000000100000001000000010000 &
b10000000100000001000000010000 )
b1011 %
b1011 '
b1011 (
1"
#1700
0"
#1710
b1000000010000000100000001 !
b1000000010000000100000001 &
b1000000010000000100000001 )
b1100 %
b1100 '
b1100 (
1"
#1720
0"
#1730
b1000100000001000100000001 !
b1000100000001000100000001 &
b1000100000001000100000001 )
b1101 %
b1101 '
b1101 (
1"
#1740
0"
#1750
b100000000000100000000 !
b100000000000100000000 &
b100000000000100000000 )
b1110 %
b1110 '
b1110 (
1"
#1760
0"
#1770
b1000100010000000000000001 !
b1000100010000000000000001 &
b1000100010000000000000001 )
b1111 %
b1111 '
b1111 (
1"
#1780
0"
#1790
b0 !
b0 &
b0 )
b10000 %
b10000 '
b10000 (
1"
#1800
0"
#1810
b100010000000000010001 !
b100010000000000010001 &
b100010000000000010001 )
b10001 %
b10001 '
b10001 (
1"
#1820
0"
#1830
b10001000000000001000100000000 !
b10001000000000001000100000000 &
b10001000000000001000100000000 )
b10010 %
b10010 '
b10010 (
1"
#1840
0"
#1850
b10000000100000001000000010000 !
b10000000100000001000000010000 &
b10000000100000001000000010000 )
b10011 %
b10011 '
b10011 (
1"
#1860
0"
#1870
b1000000010000000100000001 !
b1000000010000000100000001 &
b1000000010000000100000001 )
b10100 %
b10100 '
b10100 (
1"
#1880
0"
#1890
b1000100000001000100000001 !
b1000100000001000100000001 &
b1000100000001000100000001 )
b10101 %
b10101 '
b10101 (
1"
#1900
0"
#1910
b100000000000100000000 !
b100000000000100000000 &
b100000000000100000000 )
b10110 %
b10110 '
b10110 (
1"
#1920
0"
#1930
b1000100010000000000000001 !
b1000100010000000000000001 &
b1000100010000000000000001 )
b10111 %
b10111 '
b10111 (
1"
#1940
0"
#1950
b0 !
b0 &
b0 )
b11000 %
b11000 '
b11000 (
1"
#1960
0"
#1970
b100010000000000010001 !
b100010000000000010001 &
b100010000000000010001 )
b11001 %
b11001 '
b11001 (
1"
#1980
0"
#1990
b10001000000000001000100000000 !
b10001000000000001000100000000 &
b10001000000000001000100000000 )
b11010 %
b11010 '
b11010 (
1"
#2000
0"
#2010
b10000000100000001000000010000 !
b10000000100000001000000010000 &
b10000000100000001000000010000 )
b11011 %
b11011 '
b11011 (
1"
#2020
0"
#2030
b1000000010000000100000001 !
b1000000010000000100000001 &
b1000000010000000100000001 )
b11100 %
b11100 '
b11100 (
1"
#2040
0"
#2050
b1000100000001000100000001 !
b1000100000001000100000001 &
b1000100000001000100000001 )
b11101 %
b11101 '
b11101 (
1"
#2060
0"
#2070
b100000000000100000000 !
b100000000000100000000 &
b100000000000100000000 )
b11110 %
b11110 '
b11110 (
1"
#2080
0"
#2090
b1000100010000000000000001 !
b1000100010000000000000001 &
b1000100010000000000000001 )
b11111 %
b11111 '
b11111 (
1"
#2100
0"
#2110
b0 !
b0 &
b0 )
b100000 %
b100000 '
b100000 (
1"
#2120
0"
#2130
b100010000000000010001 !
b100010000000000010001 &
b100010000000000010001 )
b100001 %
b100001 '
b100001 (
1"
#2140
0"
#2150
b10001000000000001000100000000 !
b10001000000000001000100000000 &
b10001000000000001000100000000 )
b100010 %
b100010 '
b100010 (
1"
#2160
0"
#2170
b10000000100000001000000010000 !
b10000000100000001000000010000 &
b10000000100000001000000010000 )
b100011 %
b100011 '
b100011 (
1"
