defs.v
/*Instruction decode*/
`define opcode 6:0
`define func3 14:12
`define func7 31:25

`define rd 11:7
`define rsa 19:15
`define rsb 24:20
`define IntSize 31:0

/*The defs related to rom*/
`define InstaddrBus 31:0
`define InstBus 31:0

/*Global defs*/
`define Rsten 1'b1
`define Rstdis 1'b0
`define ZWord 32'h00000000

`define CLOG2(x) (x<=2)?1:(x<=4)?2:(x<=8)?3:(x<=16)?4:(x<=32)?5:-1

/*opcode*/

rom.v
`include "defs.v"
module rom ( input wire[31:0] addr, input wire ce, output reg[31:0] inst);

reg [31:0] rom [0:13071];

initial	$readmemh ("rom.data",rom);

always  @(addr,ce)
begin	
	if ( ce == 1'b0 )begin
		inst <= `ZWord;
	end
	else if ( ce == 1'b1)begin
		inst <= rom[addr[18:2]];
	end
end
endmodule

execute.v
`include "defs.v"

module execute #(parameter XLEN=32)(
    input [3:0] ALUcrl,
    input [XLEN-1:0] ALU_src_a,
    input [XLEN-1:0] ALU_src_b,
    output reg [XLEN-1:0] ALUOut,
    output zero );
 
 assign zero = (ALUOut==`ZWord);

always @(ALUcrl,ALU_src_a,ALU_src_b)
begin
    case(ALUcrl)
        4'b0000: ALUOut <= ALU_src_a & ALU_src_b;
        4'b0001: ALUOut <= ALU_src_a | ALU_src_b;
        4'b0010: ALUOut <= ALU_src_a + ALU_src_b;
        4'b0110: ALUOut <= ALU_src_a - ALU_src_b;
        4'b0111: ALUOut <= (ALU_src_a < ALU_src_b)?1:0;
        4'b1100: ALUOut <= ~(ALU_src_a | ALU_src_b);
        default: ALUOut <= `ZWord;
    endcase
end

endmodule

regfile.v
`include "defs.v"
module regfile #(
    parameter NUM_REGS = 32,
    parameter XLEN = 32,
    parameter RSLEN = `CLOG2(NUM_REGS))(
    input clk,
    input rst,
    /*讀取rsa*/
    input [RSLEN-1:0] rsa_a,//rsa addr
    /*讀取rsb*/
    input [RSLEN-1:0] rsb_a,
    /*寫暫存器rd*/
    input [`IntSize] wb_data,
    input [RSLEN-1:0] wb_addr,
    input wb_e,
    /*輸出data1 2*/
    output [`IntSize] rsa_o,
    output [`IntSize] rsb_o     
);
reg [XLEN-1:0] rf[0:NUM_REGS-1];

wire we = wb_e &(|wb_addr);

assign rsa_o = (we&(rsa_a==wb_addr))?wb_data:rf[rsa_a];
assign rsb_o = (we&(rsb_a==wb_addr))?wb_data:rf[rsb_a];

always @(posedge clk)
begin
    if(rst==`Rsten)
    begin
        rf[0] <= `ZWord;
        rf[1] <= `ZWord;
        rf[2] <= `ZWord;
        rf[3] <= `ZWord;
        rf[4] <= `ZWord;
        rf[5] <= `ZWord;
        rf[6] <= `ZWord;
        rf[7] <= `ZWord;
        rf[8] <= `ZWord;
        rf[9] <= `ZWord;
        rf[10] <= `ZWord;
        rf[11] <= `ZWord;
        rf[12] <= `ZWord;
        rf[13] <= `ZWord;
        rf[14] <= `ZWord;
        rf[15] <= `ZWord;
        rf[16] <= `ZWord;
        rf[17] <= `ZWord;
        rf[18] <= `ZWord;
        rf[19] <= `ZWord;
        rf[20] <= `ZWord;
        rf[21] <= `ZWord;
        rf[22] <= `ZWord;
        rf[23] <= `ZWord;
        rf[24] <= `ZWord;
        rf[25] <= `ZWord;
        rf[26] <= `ZWord;
        rf[27] <= `ZWord;
        rf[28] <= `ZWord;
        rf[29] <= `ZWord;
        rf[30] <= `ZWord;
        rf[31] <= `ZWord; 
    end
   else 
   begin
       if(we)
       begin
            rf[wb_addr] <= wb_data;   
       end
   end 
   
end

endmodule

decode.v
`include "defs.v"
module decode #(parameter XLEN = 32)(
    input rst,
    input [`InstaddrBus] pc_i,
    input [`InstBus] inst_i,
    output reg regfile_we,
    output [4:0] rsa_a_o,
    output [4:0] rsb_a_o,
    output [4:0] rsd_o,
    output [XLEN-1:0] imm_o,
    output reg ALUSrc,
    output reg [3:0] ALUOp,
    output reg memtoreg);

/*decode*/
wire [XLEN-1:0] rv32_inst = inst_i;
wire [6:0] opcode = rv32_inst[`opcode];
wire [2:0] func3 = rv32_inst[`func3];
wire [6:0] func7 = rv32_inst[`func7];
wire [XLEN-1:0] imm_I,imm_J,imm_S,imm_B,imm_U;
wire [XLEN-1:0] imm;

wire rv32_based = (opcode[1:0]==2'b11);

/*R-type*/
wire rv32_op =(opcode[6:2] == 5'b01100);
wire rv32_func3_000 = (func3==3'b000);
wire rv32_func7_0100000 = (func7==7'b0100000);
wire rv32_func7_0000000 = (func7==7'b0000000);
wire rv32_sub = (rv32_func3_000 & rv32_func7_0100000);
wire rv32_add = (rv32_func3_000 & rv32_func7_0000000);

/*I-type*/
wire rv32_op_imm = (opcode[6:2]==5'b00100);
wire rv32_addi = (rv32_func3_000 & rv32_op_imm);
assign imm_I = { {21{rv32_inst[31]}}, rv32_inst[30: 25], rv32_inst[24: 21], rv32_inst[20] };


wire rv32_imm_seli = rv32_op_imm;
assign imm = {32{rv32_imm_seli}} & imm_I;

/*Output data*/
assign rsa_a_o = rv32_inst[`rsa];
assign rsb_a_o = rv32_inst[`rsb];
assign rsd_o = rv32_inst[`rd];
assign imm_o = imm;


always @ (*)
begin
    if(rst==`Rsten)
    begin
        regfile_we <= 1'b0;//write back enable
        ALUOp <= 1'b0;
        ALUSrc <= 1'b0;
    end
    else if(rv32_op == 1'b1)
    begin
        ALUSrc <= 1'b0;//1'b0 from regfile, 1'b1 from imm 
        regfile_we <= 1'b1;
        memtoreg <= 1'b0;//write back to regfile :1'b0 from ALU,1'b1 from memory
        if(rv32_sub == 1'b1) 
        begin
            ALUOp <= 4'b0110;//ALU_SUB
        end
        else if(rv32_add)
        begin
            ALUOp <= 4'b0010;//ALU_ADD
        end
    end 
    else if(rv32_op_imm) 
    begin
        memtoreg <= 1'b0;//write back to regfile :1'b0 from ALU,1'b1 from memory
        regfile_we <= 1'b1;//write back enable
        ALUSrc <= 1'b1;  
        if(rv32_addi)
        begin
           ALUOp <= 4'b0010; 
        end
    end
end

endmodule

if_id.v
`include "defs.v"
module if_id(
    input wire clk,
    input wire rst,
    input wire [`InstaddrBus] if_pc,
    input wire [`InstBus] if_inst,
    output reg [`InstaddrBus] id_pc,
    output reg [`InstBus] id_inst 
    );
    
    always @(posedge clk)
    begin
        if(rst == `Rsten)
        begin
            id_pc <=`ZWord;
            id_inst <=`ZWord;
        end
        else
        begin
            id_pc <= if_pc;
            id_inst <= if_inst;
        end
    end
endmodule

pc_reg.v
`include "defs.v"
module pc_reg ( input wire clk, input wire rst, output reg [`InstaddrBus] pc, output reg ce);

always @(posedge clk)
begin
       if(rst==1'b1)
       	begin
       		ce <= 1'b0;
	end
	else if(rst==1'b0) 
	begin
		ce <=1'b1;
	end

end

always @(posedge clk)
begin
	if(ce==1'b0)
	begin
		pc <= 32'h0;
	end
	else if(ce==1'b1)
	begin
		pc = pc + 4'h4;
	end

end
endmodule

core_top.v
`include "defs.v"
module core_top #(parameter XLEN=32,parameter NUM_REGS=32,parameter RSLEN = `CLOG2(NUM_REGS))(
	input wire clk, 
	input wire rst,
	input wire [`InstBus] inst_i,
	output wire rom_ce0,
	output wire [`InstaddrBus] inst_pc);

	
	wire [`InstBus] inst_o;
	wire [`InstaddrBus] if_id_pc_o;
	wire [`InstBus] if_id_inst_o;

	wire [RSLEN-1:0] rsa_o;
	wire [RSLEN-1:0] rsb_o;
	wire [XLEN-1:0] rsa_data;
	wire [XLEN-1:0] rsb_data;
	wire regfile_we;
	wire [RSLEN-1:0] rsd_a;
	wire ALUSrc;
	wire [3:0] ALUOp;
	wire memtoreg;
	wire [XLEN-1:0] mem_data;
	wire [XLEN-1:0] wb_data;
	wire [XLEN-1:0] ALUOut;
	wire zero;
	wire [XLEN-1:0] imm_o;
	wire [XLEN-1:0] mux_ALUSrc;
	/*instrution fetch*/
	pc_reg pc_reg0( .clk(clk), .rst(rst), .pc(inst_pc), .ce(rom_ce0));

	if_id if_id0( .clk(clk), .rst(rst), .if_pc(inst_pc), .if_inst(inst_i), .id_pc(if_id_pc_o), .id_inst(if_id_inst_o));
	/*Instruction decode*/
	decode decode0(.rst(rst), .pc_i(if_id_pc_o), .inst_i(if_id_inst_o), .regfile_we(regfile_we), .rsa_a_o(rsa_o), .rsb_a_o(rsb_o), .rsd_o(rsd_a), .imm_o(imm_o), .ALUSrc(ALUSrc), .ALUOp(ALUOp), .memtoreg(memtoreg));

	regfile regfile(.clk(clk), .rst(rst), .rsa_a(rsa_o), .rsb_a(rsb_o), .wb_data(wb_data), .wb_addr(rsd_a), .wb_e(regfile_we), .rsa_o(rsa_data), .rsb_o(rsb_data));
	/*execute*/
	assign mux_ALUSrc = (ALUSrc == 1'b1) ? imm_o:rsb_data;
	execute execute0(.ALUcrl(ALUOp), .ALU_src_a(rsa_data), . ALU_src_b(mux_ALUSrc), .ALUOut(ALUOut), .zero(zero));
	/*memory read*/

	/*write back */
	assign wb_data = (memtoreg == 1'b1) ? mem_data:ALUOut;//data memory 待擴充

endmodule

SOPC.v
module SOPC (input clk, input rst);

wire [31:0] pc_o;
wire [31:0]  inst_o;
wire [31:0]  pc;
wire rom_ce0;

core_top core0( .clk(clk), .rst(rst), .inst_i(inst_o), .rom_ce0(rom_ce0), .inst_pc(pc));

rom rom0( .addr(pc), .ce(rom_ce0), .inst(inst_o));

endmodule

cpu0_tb.v
module cpu0_tb;
reg CLOCK;
reg rst;


// block clock register and start the clock

initial
begin
	CLOCK = 1'b0;
	forever #10 CLOCK = ~CLOCK;
end

// setup rst and stop time

initial 
begin
	rst = 1'b1;

	#190 rst = 1'b0;

	#2000 $stop;
end

// test module

SOPC cpu_rv32i( .clk(CLOCK), .rst(rst));

//core_top core_top( .clk(CLOCK), .rst(rst), .if_id_inst_o(inst), .if_id_inst_pc(pc) );
//rom rom0( .addr(inst_pc), .ce(rom_ce0), .inst(inst_o));

initial begin
	$dumpfile("cpu0_tb.vcd");
	$dumpvars(0,cpu0_tb);
end

endmodule

cpu0_tb.vcd
$date
	Fri Mar 12 11:48:30 2021
$end
$version
	Icarus Verilog
$end
$timescale
	1s
$end
$scope module cpu0_tb $end
$var reg 1 ! CLOCK $end
$var reg 1 " rst $end
$scope module cpu_rv32i $end
$var wire 1 ! clk $end
$var wire 1 " rst $end
$var wire 1 # rom_ce0 $end
$var wire 32 $ pc [31:0] $end
$var wire 32 % inst_o [31:0] $end
$scope module core0 $end
$var wire 1 ! clk $end
$var wire 32 & mem_data [31:0] $end
$var wire 1 " rst $end
$var wire 1 ' zero $end
$var wire 32 ( wb_data [31:0] $end
$var wire 5 ) rsd_a [4:0] $end
$var wire 5 * rsb_o [4:0] $end
$var wire 32 + rsb_data [31:0] $end
$var wire 5 , rsa_o [4:0] $end
$var wire 32 - rsa_data [31:0] $end
$var wire 1 # rom_ce0 $end
$var wire 1 . regfile_we $end
$var wire 32 / mux_ALUSrc [31:0] $end
$var wire 1 0 memtoreg $end
$var wire 32 1 inst_pc [31:0] $end
$var wire 32 2 inst_i [31:0] $end
$var wire 32 3 imm_o [31:0] $end
$var wire 32 4 if_id_pc_o [31:0] $end
$var wire 32 5 if_id_inst_o [31:0] $end
$var wire 1 6 ALUSrc $end
$var wire 32 7 ALUOut [31:0] $end
$var wire 4 8 ALUOp [3:0] $end
$scope module decode0 $end
$var wire 32 9 imm [31:0] $end
$var wire 32 : imm_o [31:0] $end
$var wire 1 " rst $end
$var wire 1 ; rv32_add $end
$var wire 1 < rv32_addi $end
$var wire 1 = rv32_imm_seli $end
$var wire 32 > rv32_inst [31:0] $end
$var wire 1 ? rv32_sub $end
$var wire 1 @ rv32_op_imm $end
$var wire 1 A rv32_op $end
$var wire 1 B rv32_func7_0100000 $end
$var wire 1 C rv32_func7_0000000 $end
$var wire 1 D rv32_func3_000 $end
$var wire 1 E rv32_based $end
$var wire 5 F rsd_o [4:0] $end
$var wire 5 G rsb_a_o [4:0] $end
$var wire 5 H rsa_a_o [4:0] $end
$var wire 32 I pc_i [31:0] $end
$var wire 7 J opcode [6:0] $end
$var wire 32 K inst_i [31:0] $end
$var wire 32 L imm_I [31:0] $end
$var wire 7 M func7 [6:0] $end
$var wire 3 N func3 [2:0] $end
$var reg 4 O ALUOp [3:0] $end
$var reg 1 6 ALUSrc $end
$var reg 1 0 memtoreg $end
$var reg 1 . regfile_we $end
$upscope $end
$scope module execute0 $end
$var wire 32 P ALU_src_b [31:0] $end
$var wire 4 Q ALUcrl [3:0] $end
$var wire 1 ' zero $end
$var wire 32 R ALU_src_a [31:0] $end
$var reg 32 S ALUOut [31:0] $end
$upscope $end
$scope module if_id0 $end
$var wire 1 ! clk $end
$var wire 1 " rst $end
$var wire 32 T if_pc [31:0] $end
$var wire 32 U if_inst [31:0] $end
$var reg 32 V id_inst [31:0] $end
$var reg 32 W id_pc [31:0] $end
$upscope $end
$scope module pc_reg0 $end
$var wire 1 ! clk $end
$var wire 1 " rst $end
$var reg 1 # ce $end
$var reg 32 X pc [31:0] $end
$upscope $end
$scope module regfile $end
$var wire 1 ! clk $end
$var wire 5 Y rsa_a [4:0] $end
$var wire 5 Z rsb_a [4:0] $end
$var wire 1 " rst $end
$var wire 5 [ wb_addr [4:0] $end
$var wire 32 \ wb_data [31:0] $end
$var wire 1 . wb_e $end
$var wire 1 ] we $end
$var wire 32 ^ rsb_o [31:0] $end
$var wire 32 _ rsa_o [31:0] $end
$upscope $end
$upscope $end
$scope module rom0 $end
$var wire 32 ` addr [31:0] $end
$var wire 1 # ce $end
$var reg 32 a inst [31:0] $end
$upscope $end
$upscope $end
$upscope $end
$enddefinitions $end
#0
$dumpvars
bx a
bx `
bx _
bx ^
0]
bx \
bx [
bx Z
bx Y
bx X
bx W
bx V
bx U
bx T
bx S
bx R
b0 Q
bx P
b0 O
bx N
bx M
bx L
bx K
bx J
bx I
bx H
bx G
bx F
xE
xD
xC
xB
xA
x@
x?
bx >
x=
x<
x;
bx :
bx 9
b0 8
bx 7
06
bx 5
bx 4
bx 3
bx 2
bx 1
x0
bx /
0.
bx -
bx ,
bx +
bx *
bx )
bx (
x'
bz &
bx %
bx $
x#
1"
0!
$end
#10
1'
b0 7
b0 S
b0 %
b0 2
b0 U
b0 a
0<
b0 /
b0 P
0E
0A
0=
0@
0?
1;
b0 3
b0 :
b0 9
b0 -
b0 R
b0 _
b0 +
b0 ^
b0 J
1D
b0 N
0B
1C
b0 M
b0 L
b0 ,
b0 H
b0 Y
b0 *
b0 G
b0 Z
b0 )
b0 F
b0 [
0#
b0 >
b0 5
b0 K
b0 V
b0 4
b0 I
b0 W
1!
#20
0!
#30
b0 $
b0 1
b0 T
b0 X
b0 `
1!
#40
0!
#50
1!
#60
0!
#70
1!
#80
0!
#90
1!
#100
0!
#110
1!
#120
0!
#130
1!
#140
0!
#150
1!
#160
0!
#170
1!
#180
0!
#190
b100010000000110110011 %
b100010000000110110011 2
b100010000000110110011 U
b100010000000110110011 a
1#
1!
0"
#200
0!
#210
b0 (
b0 \
1]
b10 8
b10 O
b10 Q
00
1.
1E
1A
b110011 J
b1 L
b10 ,
b10 H
b10 Y
b1 *
b1 G
b1 Z
b11 )
b11 F
b11 [
b1111100010000000110010011 %
b1111100010000000110010011 2
b1111100010000000110010011 U
b1111100010000000110010011 a
b100010000000110110011 >
b100010000000110110011 5
b100010000000110110011 K
b100010000000110110011 V
b100 $
b100 1
b100 T
b100 X
b100 `
1!
#220
0!
#230
b11111 (
b11111 \
0'
b11111 7
b11111 S
b11111 /
b11111 P
16
b11111 3
b11111 :
b11111 9
1<
0A
1=
1@
b10011 J
b11111 L
b11111 *
b11111 G
b11111 Z
b1100100000001010110011 %
b1100100000001010110011 2
b1100100000001010110011 U
b1100100000001010110011 a
b1111100010000000110010011 >
b1111100010000000110010011 5
b1111100010000000110010011 K
b1111100010000000110010011 V
b1000 4
b1000 I
b1000 W
b1000 $
b1000 1
b1000 T
b1000 X
b1000 `
1!
#240
0!
#250
b11111 (
b11111 \
0'
b11111 7
b11111 S
06
0<
b11111 /
b11111 P
1A
0=
0@
b0 3
b0 :
b0 9
b11111 +
b11111 ^
b110011 J
b11 L
b100 ,
b100 H
b100 Y
b11 *
b11 G
b11 Z
b101 )
b101 F
b101 [
b1000000001100100000001010110011 %
b1000000001100100000001010110011 2
b1000000001100100000001010110011 U
b1000000001100100000001010110011 a
b1100100000001010110011 >
b1100100000001010110011 5
b1100100000001010110011 K
b1100100000001010110011 V
b1100 $
b1100 1
b1100 T
b1100 X
b1100 `
1!
#260
0!
#270
b11111111111111111111111111100001 (
b11111111111111111111111111100001 \
b11111111111111111111111111100001 7
b11111111111111111111111111100001 S
b110 8
b110 O
b110 Q
1?
0;
1B
0C
b100000 M
b10000000011 L
b1100100000001010110011 %
b1100100000001010110011 2
b1100100000001010110011 U
b1100100000001010110011 a
b1000000001100100000001010110011 >
b1000000001100100000001010110011 5
b1000000001100100000001010110011 K
b1000000001100100000001010110011 V
b10000 4
b10000 I
b10000 W
b10000 $
b10000 1
b10000 T
b10000 X
b10000 `
1!
#280
0!
#290
b11111 (
b11111 \
b11111 7
b11111 S
b10 8
b10 O
b10 Q
0?
1;
0B
1C
b0 M
b11 L
bx %
bx 2
bx U
bx a
b1100100000001010110011 >
b1100100000001010110011 5
b1100100000001010110011 K
b1100100000001010110011 V
b10100 $
b10100 1
b10100 T
b10100 X
b10100 `
1!
#300
0!
#310
bx (
bx \
x'
bx 7
bx S
bx 3
bx :
bx 9
x<
bx /
bx P
xE
xA
x=
x@
x?
x;
bx -
bx R
bx _
bx +
bx ^
x]
bx J
xD
bx N
xB
xC
bx M
bx L
bx ,
bx H
bx Y
bx *
bx G
bx Z
bx )
bx F
bx [
bx >
bx 5
bx K
bx V
b11000 4
b11000 I
b11000 W
b11000 $
b11000 1
b11000 T
b11000 X
b11000 `
1!
#320
0!
#330
b11100 $
b11100 1
b11100 T
b11100 X
b11100 `
1!
#340
0!
#350
b100000 4
b100000 I
b100000 W
b100000 $
b100000 1
b100000 T
b100000 X
b100000 `
1!
#360
0!
#370
b100100 $
b100100 1
b100100 T
b100100 X
b100100 `
1!
#380
0!
#390
b101000 4
b101000 I
b101000 W
b101000 $
b101000 1
b101000 T
b101000 X
b101000 `
1!
#400
0!
#410
b101100 $
b101100 1
b101100 T
b101100 X
b101100 `
1!
#420
0!
#430
b110000 4
b110000 I
b110000 W
b110000 $
b110000 1
b110000 T
b110000 X
b110000 `
1!
#440
0!
#450
b110100 $
b110100 1
b110100 T
b110100 X
b110100 `
1!
#460
0!
#470
b111000 4
b111000 I
b111000 W
b111000 $
b111000 1
b111000 T
b111000 X
b111000 `
1!
#480
0!
#490
b111100 $
b111100 1
b111100 T
b111100 X
b111100 `
1!
#500
0!
#510
b1000000 4
b1000000 I
b1000000 W
b1000000 $
b1000000 1
b1000000 T
b1000000 X
b1000000 `
1!
#520
0!
#530
b1000100 $
b1000100 1
b1000100 T
b1000100 X
b1000100 `
1!
#540
0!
#550
b1001000 4
b1001000 I
b1001000 W
b1001000 $
b1001000 1
b1001000 T
b1001000 X
b1001000 `
1!
#560
0!
#570
b1001100 $
b1001100 1
b1001100 T
b1001100 X
b1001100 `
1!
#580
0!
#590
b1010000 4
b1010000 I
b1010000 W
b1010000 $
b1010000 1
b1010000 T
b1010000 X
b1010000 `
1!
#600
0!
#610
b1010100 $
b1010100 1
b1010100 T
b1010100 X
b1010100 `
1!
#620
0!
#630
b1011000 4
b1011000 I
b1011000 W
b1011000 $
b1011000 1
b1011000 T
b1011000 X
b1011000 `
1!
#640
0!
#650
b1011100 $
b1011100 1
b1011100 T
b1011100 X
b1011100 `
1!
#660
0!
#670
b1100000 4
b1100000 I
b1100000 W
b1100000 $
b1100000 1
b1100000 T
b1100000 X
b1100000 `
1!
#680
0!
#690
b1100100 $
b1100100 1
b1100100 T
b1100100 X
b1100100 `
1!
#700
0!
#710
b1101000 4
b1101000 I
b1101000 W
b1101000 $
b1101000 1
b1101000 T
b1101000 X
b1101000 `
1!
#720
0!
#730
b1101100 $
b1101100 1
b1101100 T
b1101100 X
b1101100 `
1!
#740
0!
#750
b1110000 4
b1110000 I
b1110000 W
b1110000 $
b1110000 1
b1110000 T
b1110000 X
b1110000 `
1!
#760
0!
#770
b1110100 $
b1110100 1
b1110100 T
b1110100 X
b1110100 `
1!
#780
0!
#790
b1111000 4
b1111000 I
b1111000 W
b1111000 $
b1111000 1
b1111000 T
b1111000 X
b1111000 `
1!
#800
0!
#810
b1111100 $
b1111100 1
b1111100 T
b1111100 X
b1111100 `
1!
#820
0!
#830
b10000000 4
b10000000 I
b10000000 W
b10000000 $
b10000000 1
b10000000 T
b10000000 X
b10000000 `
1!
#840
0!
#850
b10000100 $
b10000100 1
b10000100 T
b10000100 X
b10000100 `
1!
#860
0!
#870
b10001000 4
b10001000 I
b10001000 W
b10001000 $
b10001000 1
b10001000 T
b10001000 X
b10001000 `
1!
#880
0!
#890
b10001100 $
b10001100 1
b10001100 T
b10001100 X
b10001100 `
1!
#900
0!
#910
b10010000 4
b10010000 I
b10010000 W
b10010000 $
b10010000 1
b10010000 T
b10010000 X
b10010000 `
1!
#920
0!
#930
b10010100 $
b10010100 1
b10010100 T
b10010100 X
b10010100 `
1!
#940
0!
#950
b10011000 4
b10011000 I
b10011000 W
b10011000 $
b10011000 1
b10011000 T
b10011000 X
b10011000 `
1!
#960
0!
#970
b10011100 $
b10011100 1
b10011100 T
b10011100 X
b10011100 `
1!
#980
0!
#990
b10100000 4
b10100000 I
b10100000 W
b10100000 $
b10100000 1
b10100000 T
b10100000 X
b10100000 `
1!
#1000
0!
#1010
b10100100 $
b10100100 1
b10100100 T
b10100100 X
b10100100 `
1!
#1020
0!
#1030
b10101000 4
b10101000 I
b10101000 W
b10101000 $
b10101000 1
b10101000 T
b10101000 X
b10101000 `
1!
#1040
0!
#1050
b10101100 $
b10101100 1
b10101100 T
b10101100 X
b10101100 `
1!
#1060
0!
#1070
b10110000 4
b10110000 I
b10110000 W
b10110000 $
b10110000 1
b10110000 T
b10110000 X
b10110000 `
1!
#1080
0!
#1090
b10110100 $
b10110100 1
b10110100 T
b10110100 X
b10110100 `
1!
#1100
0!
#1110
b10111000 4
b10111000 I
b10111000 W
b10111000 $
b10111000 1
b10111000 T
b10111000 X
b10111000 `
1!
#1120
0!
#1130
b10111100 $
b10111100 1
b10111100 T
b10111100 X
b10111100 `
1!
#1140
0!
#1150
b11000000 4
b11000000 I
b11000000 W
b11000000 $
b11000000 1
b11000000 T
b11000000 X
b11000000 `
1!
#1160
0!
#1170
b11000100 $
b11000100 1
b11000100 T
b11000100 X
b11000100 `
1!
#1180
0!
#1190
b11001000 4
b11001000 I
b11001000 W
b11001000 $
b11001000 1
b11001000 T
b11001000 X
b11001000 `
1!
#1200
0!
#1210
b11001100 $
b11001100 1
b11001100 T
b11001100 X
b11001100 `
1!
#1220
0!
#1230
b11010000 4
b11010000 I
b11010000 W
b11010000 $
b11010000 1
b11010000 T
b11010000 X
b11010000 `
1!
#1240
0!
#1250
b11010100 $
b11010100 1
b11010100 T
b11010100 X
b11010100 `
1!
#1260
0!
#1270
b11011000 4
b11011000 I
b11011000 W
b11011000 $
b11011000 1
b11011000 T
b11011000 X
b11011000 `
1!
#1280
0!
#1290
b11011100 $
b11011100 1
b11011100 T
b11011100 X
b11011100 `
1!
#1300
0!
#1310
b11100000 4
b11100000 I
b11100000 W
b11100000 $
b11100000 1
b11100000 T
b11100000 X
b11100000 `
1!
#1320
0!
#1330
b11100100 $
b11100100 1
b11100100 T
b11100100 X
b11100100 `
1!
#1340
0!
#1350
b11101000 4
b11101000 I
b11101000 W
b11101000 $
b11101000 1
b11101000 T
b11101000 X
b11101000 `
1!
#1360
0!
#1370
b11101100 $
b11101100 1
b11101100 T
b11101100 X
b11101100 `
1!
#1380
0!
#1390
b11110000 4
b11110000 I
b11110000 W
b11110000 $
b11110000 1
b11110000 T
b11110000 X
b11110000 `
1!
#1400
0!
#1410
b11110100 $
b11110100 1
b11110100 T
b11110100 X
b11110100 `
1!
#1420
0!
#1430
b11111000 4
b11111000 I
b11111000 W
b11111000 $
b11111000 1
b11111000 T
b11111000 X
b11111000 `
1!
#1440
0!
#1450
b11111100 $
b11111100 1
b11111100 T
b11111100 X
b11111100 `
1!
#1460
0!
#1470
b100000000 4
b100000000 I
b100000000 W
b100000000 $
b100000000 1
b100000000 T
b100000000 X
b100000000 `
1!
#1480
0!
#1490
b100000100 $
b100000100 1
b100000100 T
b100000100 X
b100000100 `
1!
#1500
0!
#1510
b100001000 4
b100001000 I
b100001000 W
b100001000 $
b100001000 1
b100001000 T
b100001000 X
b100001000 `
1!
#1520
0!
#1530
b100001100 $
b100001100 1
b100001100 T
b100001100 X
b100001100 `
1!
#1540
0!
#1550
b100010000 4
b100010000 I
b100010000 W
b100010000 $
b100010000 1
b100010000 T
b100010000 X
b100010000 `
1!
#1560
0!
#1570
b100010100 $
b100010100 1
b100010100 T
b100010100 X
b100010100 `
1!
#1580
0!
#1590
b100011000 4
b100011000 I
b100011000 W
b100011000 $
b100011000 1
b100011000 T
b100011000 X
b100011000 `
1!
#1600
0!
#1610
b100011100 $
b100011100 1
b100011100 T
b100011100 X
b100011100 `
1!
#1620
0!
#1630
b100100000 4
b100100000 I
b100100000 W
b100100000 $
b100100000 1
b100100000 T
b100100000 X
b100100000 `
1!
#1640
0!
#1650
b100100100 $
b100100100 1
b100100100 T
b100100100 X
b100100100 `
1!
#1660
0!
#1670
b100101000 4
b100101000 I
b100101000 W
b100101000 $
b100101000 1
b100101000 T
b100101000 X
b100101000 `
1!
#1680
0!
#1690
b100101100 $
b100101100 1
b100101100 T
b100101100 X
b100101100 `
1!
#1700
0!
#1710
b100110000 4
b100110000 I
b100110000 W
b100110000 $
b100110000 1
b100110000 T
b100110000 X
b100110000 `
1!
#1720
0!
#1730
b100110100 $
b100110100 1
b100110100 T
b100110100 X
b100110100 `
1!
#1740
0!
#1750
b100111000 4
b100111000 I
b100111000 W
b100111000 $
b100111000 1
b100111000 T
b100111000 X
b100111000 `
1!
#1760
0!
#1770
b100111100 $
b100111100 1
b100111100 T
b100111100 X
b100111100 `
1!
#1780
0!
#1790
b101000000 4
b101000000 I
b101000000 W
b101000000 $
b101000000 1
b101000000 T
b101000000 X
b101000000 `
1!
#1800
0!
#1810
b101000100 $
b101000100 1
b101000100 T
b101000100 X
b101000100 `
1!
#1820
0!
#1830
b101001000 4
b101001000 I
b101001000 W
b101001000 $
b101001000 1
b101001000 T
b101001000 X
b101001000 `
1!
#1840
0!
#1850
b101001100 $
b101001100 1
b101001100 T
b101001100 X
b101001100 `
1!
#1860
0!
#1870
b101010000 4
b101010000 I
b101010000 W
b101010000 $
b101010000 1
b101010000 T
b101010000 X
b101010000 `
1!
#1880
0!
#1890
b101010100 $
b101010100 1
b101010100 T
b101010100 X
b101010100 `
1!
#1900
0!
#1910
b101011000 4
b101011000 I
b101011000 W
b101011000 $
b101011000 1
b101011000 T
b101011000 X
b101011000 `
1!
#1920
0!
#1930
b101011100 $
b101011100 1
b101011100 T
b101011100 X
b101011100 `
1!
#1940
0!
#1950
b101100000 4
b101100000 I
b101100000 W
b101100000 $
b101100000 1
b101100000 T
b101100000 X
b101100000 `
1!
#1960
0!
#1970
b101100100 $
b101100100 1
b101100100 T
b101100100 X
b101100100 `
1!
#1980
0!
#1990
b101101000 4
b101101000 I
b101101000 W
b101101000 $
b101101000 1
b101101000 T
b101101000 X
b101101000 `
1!
#2000
0!
#2010
b101101100 $
b101101100 1
b101101100 T
b101101100 X
b101101100 `
1!
#2020
0!
#2030
b101110000 4
b101110000 I
b101110000 W
b101110000 $
b101110000 1
b101110000 T
b101110000 X
b101110000 `
1!
#2040
0!
#2050
b101110100 $
b101110100 1
b101110100 T
b101110100 X
b101110100 `
1!
#2060
0!
#2070
b101111000 4
b101111000 I
b101111000 W
b101111000 $
b101111000 1
b101111000 T
b101111000 X
b101111000 `
1!
#2080
0!
#2090
b101111100 $
b101111100 1
b101111100 T
b101111100 X
b101111100 `
1!
#2100
0!
#2110
b110000000 4
b110000000 I
b110000000 W
b110000000 $
b110000000 1
b110000000 T
b110000000 X
b110000000 `
1!
#2120
0!
#2130
b110000100 $
b110000100 1
b110000100 T
b110000100 X
b110000100 `
1!
#2140
0!
#2150
b110001000 4
b110001000 I
b110001000 W
b110001000 $
b110001000 1
b110001000 T
b110001000 X
b110001000 `
1!
#2160
0!
#2170
b110001100 $
b110001100 1
b110001100 T
b110001100 X
b110001100 `
1!
